trustplutusnm/__init__.py
trustplutusnm/main.py
trustplutusnm/utils/__init__.py
trustplutusnm/utils/logs.py
trustplutusnm/utils/webscraping.py
trustplutusnm-1.1.dist-info/LICENSE
trustplutusnm-1.1.dist-info/METADATA
trustplutusnm-1.1.dist-info/WHEEL
trustplutusnm-1.1.dist-info/RECORD
